CHANGELOG.rst
LICENSE.txt
MANIFEST.in
README.rst
pyproject.toml
requirements.txt
setup.cfg
setup.py
core_optimizer/__init__.py
core_optimizer/__main__.py
core_optimizer/_version_.py
core_optimizer/core_optimizer.py
core_optimizer.egg-info/PKG-INFO
core_optimizer.egg-info/SOURCES.txt
core_optimizer.egg-info/dependency_links.txt
core_optimizer.egg-info/requires.txt
core_optimizer.egg-info/top_level.txt
docs/documentation.pdf