Metadata-Version: 1.2
Name: core-optimizer
Version: 1.1.0
Summary: Continual Resilient (CoRe) optimizer for PyTorch
Home-page: https://github.com/ReiherGroup/CoRe_optimizer
Author: Marco Eckhoff, Markus Reiher
Author-email: lifelong_ml@phys.chem.ethz.ch
License: BSD (3-clause)
Platform: UNKNOWN
Classifier: Programming Language :: Python
Classifier: Development Status :: 5 - Production/Stable
Classifier: Intended Audience :: Science/Research
Classifier: License :: OSI Approved :: BSD License
Classifier: Natural Language :: English
Requires-Python: >=3.8
